{
    "$schema": "https://schema.management.azure.com/schemas/2019-04-01/deploymentParameters.json#",
    "contentVersion": "1.0.0.0",
    "parameters": {
        "locationSite1": {
            "value": "japaneast"
        },
        "locationSite2": {
            "value": "japanwest"
        },
        "vmAdminUsername": {
            "value": "vmAdminUsername"
        },
        "vmAdminPassword": {
            "value": "vmAdminPassword"
        },
        "deployBastion": {
            "value": false
        },
        "deployOnprecloud": {
            "value": false
        },
        "enablediagnostics": {
            "value": false
        }
    }
}